sled/__init__.py
sled/sled.py
sled-0.0.4.dist-info/LICENSE
sled-0.0.4.dist-info/METADATA
sled-0.0.4.dist-info/WHEEL
sled-0.0.4.dist-info/top_level.txt
sled-0.0.4.dist-info/RECORD
