Metadata-Version: 2.1
Name: sled
Version: 0.0.4
Summary: some useful async schedule class, which use coroutine to make more efficient, refer to the standard library `sched`
Home-page: https://github.com/Yyonging/asyncsched
Author: duanyongqiang
Author-email: sysuduanyongqiang@163.com
License: UNKNOWN
Project-URL: Bug Tracker, https://github.com/Yyonging/asyncsched/issues
Platform: UNKNOWN
Classifier: Programming Language :: Python :: 3
Classifier: License :: OSI Approved :: MIT License
Classifier: Operating System :: OS Independent
Requires-Python: >=3.6
License-File: LICENSE
